steam2starbound/__main__.py
steam2starbound-1.0.1.dist-info/LICENSE
steam2starbound-1.0.1.dist-info/METADATA
steam2starbound-1.0.1.dist-info/WHEEL
steam2starbound-1.0.1.dist-info/entry_points.txt
steam2starbound-1.0.1.dist-info/top_level.txt
steam2starbound-1.0.1.dist-info/RECORD
