Metadata-Version: 2.1
Name: steam2starbound
Version: 1.0.1
Summary: Copies mods from steam workshop to the starbound directory.
Home-page: https://git.brokenmouse.studio/ever/steam2starbound
Author: EV3R4
License: MIT
Keywords: starbound
Platform: UNKNOWN
Classifier: Development Status :: 5 - Production/Stable
Classifier: Intended Audience :: System Administrators
Classifier: Topic :: Games/Entertainment
Classifier: Topic :: Utilities
Classifier: License :: OSI Approved :: MIT License
Classifier: Operating System :: OS Independent
Classifier: Natural Language :: English
License-File: LICENSE
